sqblack/__init__.py
sqblack/_version.py
sqblack/cli.py
SQ_Black-2019.1.15.dist-info/LICENSE
SQ_Black-2019.1.15.dist-info/METADATA
SQ_Black-2019.1.15.dist-info/WHEEL
SQ_Black-2019.1.15.dist-info/entry_points.txt
SQ_Black-2019.1.15.dist-info/top_level.txt
SQ_Black-2019.1.15.dist-info/RECORD
